<decisionTree name="WAQSomat">
    <classes>
        <class name="WOLKE" value="1" color="WHITE"/>
        <class name="WATT" value="5" color="YELLOW"/>
        <class name="SCHLICK" value="6" color="23,67,212"/>
        <class name="WIESE" value="9" color="GREEN"/>
    </classes>

    <decision name="Viel dreizehn" term="radiance_13 &lt; 100">
        <yes>
            <decision name="Wolke?" term="radiance_12 > 50">
                <yes>WOLKE</yes>
                <no>WATT</no>
            </decision>
        </yes>
        <no>
            <decision name="Schaschlik?" term="radiance_7 > 50 AND !l1_flags.LAND_OCEAN">
                <yes>SCHLICK</yes>
                <no>WIESE</no>
            </decision>
        </no>
    </decision>
</decisionTree>
